mirrormate/__init__.py
mirrormate/cli.py
mirrormate/clone.py
mirrormate-3.0.0.dist-info/METADATA
mirrormate-3.0.0.dist-info/WHEEL
mirrormate-3.0.0.dist-info/entry_points.txt
mirrormate-3.0.0.dist-info/top_level.txt
mirrormate-3.0.0.dist-info/RECORD
