Metadata-Version: 2.1
Name: mirrormate
Version: 3.0.0
Summary: A simple package to clone websites and download specific files using wget.
Home-page: https://github.com/ByteBreach/MirrorMate
Author: MrFidal
Author-email: mrfidal@proton.me
License: MIT
Keywords: mirrormate clone websites wget download files
Classifier: Development Status :: 5 - Production/Stable
Classifier: Intended Audience :: Developers
Classifier: Intended Audience :: System Administrators
Classifier: License :: OSI Approved :: MIT License
Classifier: Programming Language :: Python :: 3
Classifier: Programming Language :: Python :: 3.11
Classifier: Topic :: Internet :: WWW/HTTP
Classifier: Operating System :: OS Independent
Classifier: Natural Language :: English
Requires-Python: >=3.6
